osm_runner/__init__.py
osm_runner/runner.py
osm_runner-0.0.3.dist-info/METADATA
osm_runner-0.0.3.dist-info/WHEEL
osm_runner-0.0.3.dist-info/top_level.txt
osm_runner-0.0.3.dist-info/RECORD
