Metadata-Version: 2.1
Name: osm-runner
Version: 0.0.3
Summary: A simple ORM that leverages the GeoAccessor of the ArcGIS API for Python to integrate OSM data with the ArcGIS platform.
Home-page: https://github.com/Jwmazzi/osm_runner
Author: Jeffrey Scarmazzi
Author-email: jscarmazzi@esri.com
License: UNKNOWN
Download-URL: https://github.com/jwmazzi/osm_runner/archive/0.0.3.tar.gz
Keywords: ArcGIS API for Python,OpenStreetMap
Platform: UNKNOWN
Requires-Dist: requests
Requires-Dist: pandas
Requires-Dist: arcgis
